LICENSE
MANIFEST.in
README.rst
requirements.txt
setup.cfg
setup.py
tests.py
Heatshrink.egg-info/PKG-INFO
Heatshrink.egg-info/SOURCES.txt
Heatshrink.egg-info/dependency_links.txt
Heatshrink.egg-info/top_level.txt
heatshrink/heatshrink_common.h
heatshrink/heatshrink_config.h
heatshrink/heatshrink_decoder.c
heatshrink/heatshrink_decoder.h
heatshrink/heatshrink_encoder.c
heatshrink/heatshrink_encoder.h
src/cheatshrink.pxd
src/heatshrink.c
src/heatshrink.pyx