Metadata-Version: 1.1
Name: Heatshrink
Version: 0.2.4
Summary: Python bindings to the heatshrink library
Home-page: https://github.com/johan-sports/pyheatshrink
Author: Antonis Kalou @ JOHAN Sports
Author-email: antonis@johan-sports.com
License: ISC
Keywords: compression bindings heatshrink LZSS
Platform: UNKNOWN
Classifier: Development Status :: 3 - Alpha
Classifier: Intended Audience :: Developers
Classifier: Topic :: System :: Archiving :: Compression
Classifier: License :: OSI Approved :: ISC License (ISCL)
Classifier: Programming Language :: Python :: 2
Classifier: Programming Language :: Python :: 2.6
Classifier: Programming Language :: Python :: 2.7
Classifier: Programming Language :: Python :: 3
Classifier: Programming Language :: Python :: 3.3
Classifier: Programming Language :: Python :: 3.4
Classifier: Programming Language :: Python :: 3.5
